vulkan_utils/__init__.py
vulkan_utils/cli.py
vulkan_utils/sdk.py
vulkan_utils-0.1.9.dist-info/licenses/LICENSE
vulkan_utils-0.1.9.dist-info/METADATA
vulkan_utils-0.1.9.dist-info/WHEEL
vulkan_utils-0.1.9.dist-info/entry_points.txt
vulkan_utils-0.1.9.dist-info/top_level.txt
vulkan_utils-0.1.9.dist-info/RECORD
