Metadata-Version: 2.4
Name: vulkan_utils
Version: 0.1.9
Summary: A simple CLI utility for Vulkan SDK operations
Project-URL: homepage, https://github.com/msemelman/vulkan-utils
Project-URL: source, https://github.com/msemelman/vulkan-utils
Project-URL: issues, https://github.com/msemelman/vulkan-utils/issues
Project-URL: documentation, https://msemelman.github.io/vulkan_utils/
Requires-Python: >=3.10
License-File: LICENSE
Requires-Dist: click>=8.0.0
Requires-Dist: requests>=2.28.0
Requires-Dist: pydantic>=2.0.0
Dynamic: license-file
